doris_alchemy/__init__.py
doris_alchemy/const.py
doris_alchemy/datatype.py
doris_alchemy/dialect.py
doris_alchemy/orm_base.py
doris_alchemy/util.py
doris_alchemy-0.2.11.dist-info/LICENSE
doris_alchemy-0.2.11.dist-info/METADATA
doris_alchemy-0.2.11.dist-info/WHEEL
doris_alchemy-0.2.11.dist-info/entry_points.txt
doris_alchemy-0.2.11.dist-info/top_level.txt
doris_alchemy-0.2.11.dist-info/RECORD
