Metadata-Version: 2.2
Name: doris-alchemy
Version: 0.2.11
Summary: Apache Doris dialect for SQLAlchemy
Author-email: vtsiura <morfey.rulit@gmail.com>
Maintainer-email: vtsiura <morfey.rulit@gmail.com>
License: Apache Software License
Project-URL: Homepage, https://github.com/VasilevsVV/doris-alchemy
Project-URL: Issues, https://github.com/VasilevsVV/doris-alchemy/issues
Keywords: Apache Doris,SQLAlchemy
Classifier: Development Status :: 2 - Pre-Alpha
Classifier: Programming Language :: Python :: 3
Requires-Python: >=3.10.12
License-File: LICENSE
Requires-Dist: sqlalchemy>=2.0
Provides-Extra: mysqldb
Requires-Dist: mysqlclient>=2.1.0; extra == "mysqldb"
Provides-Extra: pymysql
Requires-Dist: pymysql; extra == "pymysql"
